LICENSE
MANIFEST.in
README.md
setup.py
bin/croutera
croutera/__init__.py
croutera/cli.py
croutera/commands.py
croutera/exceptions.py
croutera/extractor.py
croutera/runner.py
croutera/version.py
croutera.egg-info/PKG-INFO
croutera.egg-info/SOURCES.txt
croutera.egg-info/dependency_links.txt
croutera.egg-info/not-zip-safe
croutera.egg-info/requires.txt
croutera.egg-info/top_level.txt
croutera/models/__init__.py
croutera/models/base.py
croutera/models/routers.py
croutera/models/cisco/__init__.py
croutera/models/cisco/dpc3928s.py
croutera/models/dlink/__init__.py
croutera/models/dlink/dir610.py
croutera/models/tplink/__init__.py
croutera/models/tplink/tlwrbased.py
croutera/models/tplink/wr340g.py
croutera/models/tplink/wr720n.py
tests/__init__.py
tests/test_cli.py
tests/test_extractor.py
tests/test_runner.py
tests/models/__init__.py
tests/models/test_base.py
tests/models/test_router.py