Metadata-Version: 1.0
Name: croutera
Version: 0.0.6
Summary: Simple Cli Router Admin
Home-page: https://github.com/cristianoliveira/croutera
Author: Cristian Oliveira
Author-email: contato@cristianoliveira.com.br
License: MIT
Platform: UNKNOWN
